houndapi/__init__.py
houndapi/logger.py
houndapi/client/__init__.py
houndapi/client/client.py
houndapi/client/methods/__init__.py
houndapi/client/methods/poll.py
houndapi/client/methods/subscribe.py
houndapi/client/methods/unsubscribe.py
houndapi/schema/__init__.py
houndapi/schema/context.py
houndapi/schema/subscription.py
houndapi/schema/responses/__init__.py
houndapi/schema/responses/subscription.py
etherhound_api-1.0.0.dist-info/METADATA
etherhound_api-1.0.0.dist-info/WHEEL
etherhound_api-1.0.0.dist-info/top_level.txt
etherhound_api-1.0.0.dist-info/RECORD
