Metadata-Version: 2.4
Name: etherhound-api
Version: 1.0.0
Summary: EtherHound API - API Client for EtherHound Core
Author: Spicy Penguin
Requires-Python: >=3.11
Requires-Dist: aiohttp
Requires-Dist: pydantic
Dynamic: requires-python
